logic_lm_mcp/__init__.py
logic_lm_mcp/asp_templates.py
logic_lm_mcp/logic_framework.py
logic_lm_mcp/main.py
logic_lm_mcp_server-1.0.1.dist-info/METADATA
logic_lm_mcp_server-1.0.1.dist-info/WHEEL
logic_lm_mcp_server-1.0.1.dist-info/entry_points.txt
logic_lm_mcp_server-1.0.1.dist-info/licenses/LICENSE
logic_lm_mcp_server-1.0.1.dist-info/RECORD
