Metadata-Version: 2.4
Name: logic-lm-mcp-server
Version: 1.0.1
Summary: A Model Context Protocol server that provides symbolic reasoning capabilities using Logic-LM framework and Answer Set Programming
Project-URL: Homepage, https://github.com/stevenwangbe/logic-lm-mcp-server
Project-URL: Repository, https://github.com/stevenwangbe/logic-lm-mcp-server
Project-URL: Issues, https://github.com/stevenwangbe/logic-lm-mcp-server/issues
Project-URL: Documentation, https://github.com/stevenwangbe/logic-lm-mcp-server/blob/main/README.md
Author-email: Steven Wang <stevenwangbe@gmail.com>
License: MIT License
License-File: LICENSE
Keywords: answer-set-programming,asp,clingo,logic,mcp,reasoning,symbolic-solver
Classifier: Development Status :: 4 - Beta
Classifier: Intended Audience :: Developers
Classifier: Intended Audience :: Science/Research
Classifier: License :: OSI Approved :: MIT License
Classifier: Operating System :: OS Independent
Classifier: Programming Language :: Python :: 3
Classifier: Programming Language :: Python :: 3.8
Classifier: Programming Language :: Python :: 3.9
Classifier: Programming Language :: Python :: 3.10
Classifier: Programming Language :: Python :: 3.11
Classifier: Programming Language :: Python :: 3.12
Classifier: Topic :: Scientific/Engineering :: Artificial Intelligence
Classifier: Topic :: Scientific/Engineering :: Information Analysis
Classifier: Topic :: Software Development :: Libraries :: Python Modules
Requires-Python: >=3.8
Requires-Dist: fastmcp>=2.0.0
Requires-Dist: pydantic>=2.0.0
Requires-Dist: typing-extensions>=4.0.0
Provides-Extra: all
Requires-Dist: black>=23.0.0; extra == 'all'
Requires-Dist: clingo>=5.8.0; extra == 'all'
Requires-Dist: pytest-asyncio>=0.21.0; extra == 'all'
Requires-Dist: pytest>=7.0.0; extra == 'all'
Requires-Dist: ruff>=0.1.0; extra == 'all'
Provides-Extra: dev
Requires-Dist: black>=23.0.0; extra == 'dev'
Requires-Dist: pytest-asyncio>=0.21.0; extra == 'dev'
Requires-Dist: pytest>=7.0.0; extra == 'dev'
Requires-Dist: ruff>=0.1.0; extra == 'dev'
Provides-Extra: solver
Requires-Dist: clingo>=5.8.0; extra == 'solver'
